{
  "assertOn": 1,
  "nUnitTraceBufSize": 8,
  "wAddr": 48,
  "wCacheLineOffset": 6,
  "wFPortId": 2,
  "configuration": 0,
  "wData": 256,
  "wLargestEndpoint": 40,
  "enableDoublePortBuffer": 0,
  "engVerId": 0,
  "implVerId": 0,
  "useExternalMemory": 0,
  "readBufferDepth": 4,
  "fnErrDetectCorrect": "NONE",
  "fnNativeInterface": "AXI4",
  "useAddrTranslation": 0,
  "useResiliency": 0,
  "usePma": 0,
  "ResilienceInfo": {
    "enableUnitDuplication": 0,
    "enableNativeIntfProtection": 0,
    "nResiliencyDelay": 1,
    "fnResiliencyProtectionType": "none"
  },
  "PmaInfo": {"fnPmaInterfaceType": "Q", "wActive": 1},
  "cmType": {
    "CmdRdCln": "8'h01",
    "CmdRdNshDty": "8'h02",
    "CmdRdVld": "8'h03",
    "CmdRdUnq": "8'h04",
    "CmdClnUnq": "8'h05",
    "CmdMkUnq": "8'h06",
    "CmdRdNitc": "8'h07",
    "CmdClnVld": "8'h08",
    "CmdClnInv": "8'h09",
    "CmdMkInv": "8'h0A",
    "CmdRdNC": "8'h0B",
    "CmdDvmMsg": "8'h0F",
    "CmdWrUnqPtl": "8'h10",
    "CmdWrUnqFull": "8'h11",
    "CmdWrAtm": "8'h12",
    "CmdRdAtm": "8'h13",
    "CmdWrBkFull": "8'h14",
    "CmdWrClnFull": "8'h15",
    "CmdWrEvict": "8'h16",
    "CmdEvict": "8'h17",
    "CmdWrBkPtl": "8'h18",
    "CmdWrClnPtl": "8'h19",
    "CmdWrNCPtl": "8'h20",
    "CmdWrNCFull": "8'h21",
    "CmdWrStshFull": "8'h22",
    "CmdWrStshPtl": "8'h23",
    "CmdLdCchShd": "8'h24",
    "CmdLdCchUnq": "8'h25",
    "CmdRdNitcCI": "8'h26",
    "CmdRdNitcMI": "8'h27",
    "CmdClnShPsist": "8'h28",
    "CmdSwapAtm": "8'h29",
    "CmdCompAtm": "8'h2A",
    "CmdPref": "8'h2B",
    "SnpClnDtr": "8'h41",
    "SnpNitc": "8'h42",
    "SnpVldDtr": "8'h43",
    "SnpInvDtr": "8'h44",
    "SnpInvDtw": "8'h45",
    "SnpInv": "8'h46",
    "SnpClnDtw": "8'h48",
    "SnpNoSDInt": "8'h4A",
    "SnpInvStsh": "8'h4B",
    "SnpUnqStsh": "8'h4C",
    "SnpStshShd": "8'h4D",
    "SnpStshUnq": "8'h4E",
    "SnpDvmMsg": "8'h4F",
    "SnpNitcCI": "8'h50",
    "SnpNitcMI": "8'h51",
    "MrdRdCln": "8'h60",
    "MrdRdWSCln": "8'h61",
    "MrdRdWUCln": "8'h62",
    "MrdRdWU": "8'h63",
    "MrdRdWInv": "8'h64",
    "MrdPref": "8'h65",
    "MrdCln": "8'h66",
    "MrdInv": "8'h67",
    "MrdFlush": "8'h68",
    "UpdInv": "8'h70",
    "UpdSCln": "8'h71",
    "HntRead": "8'h78",
    "StrReq": "8'h7A",
    "TunReq": "8'h7B",
    "RbrReq": "8'h7C",
    "RbUReq": "8'h7D",
    "DtrDataInv": "8'h80",
    "DtrDataSCln": "8'h81",
    "DtrDataSDty": "8'h82",
    "DtrDataUCln": "8'h83",
    "DtrDataUDty": "8'h84",
    "DtwNullData": "8'h90",
    "DtwDataFullCln": "8'h91",
    "DtwDataPtlDty": "8'h92",
    "DtwDataFullDty": "8'h93",
    "DtwMrgMrdInv": "8'h98",
    "DtwMrgMrdSCln": "8'h99",
    "DtwMrgMrdSDty": "8'h9A",
    "DtwMrgMrdUCln": "8'h9B",
    "DtwMrgMrdUDty": "8'h9C",
    "CCmdRsp": "8'hF0",
    "NCCmdRsp": "8'hF1",
    "SnpRsp": "8'hF2",
    "DtwRsp": "8'hF3",
    "DtrReq": "8'h80",
    "DtrRsp": "8'hF4",
    "HntRsp": "8'hF5",
    "MrdRsp": "8'hF6",
    "StrRsp": "8'hF7",
    "UpdRsp": "8'hF8",
    "RbrRsp": "8'hF9",
    "RbuRsp": "8'hFA",
    "TunRsp": "8'hFB",
    "CmpRsp": "8'hFC",
    "CmeRsp": "8'hFD",
    "TreRsp": "8'hFE"
  },
  "concParams": {
    "hdrParams": {
      "wTargetId": 6,
      "wInitiatorId": 6,
      "wCmType": 8,
      "wMsgId": 7,
      "wHProt": 0,
      "wTTier": 0,
      "wSteering": 0,
      "wPriority": 0,
      "wQl": 0
    },
    "cmdReqParams": {
      "wNdpAux": 0,
      "wQos": 0,
      "wTof": 3,
      "wDId": 4,
      "wIntfSize": 2,
      "wSize": 3,
      "wMpf2": 10,
      "wMpf1": 8,
      "wTM": 1,
      "wRL": 2,
      "wLK": 2,
      "wOR": 2,
      "wPR": 1,
      "wNS": 1,
      "wES": 1,
      "wEN": 1,
      "wST": 1,
      "wCH": 1,
      "wCA": 1,
      "wAC": 1,
      "wVZ": 1,
      "wAddr": 48,
      "wCmStatus": 8,
      "wMProt": 0
    },
    "dtrReqParams": {
      "wNdpAux": 0,
      "wMpf1": 8,
      "wTM": 1,
      "wRL": 2,
      "wEO": 0,
      "wCmStatus": 8,
      "wMsgId": 7,
      "wData": 256,
      "wBE": 32,
      "wDwId": 12,
      "wDBad": 4,
      "wDProt": 0,
      "wUser": 0,
      "wMProt": 0
    },
    "cmdRspParams": {"wCmStatus": 8, "wMsgId": 7, "wMProt": 0},
    "dtrRspParams": {"wRL": 2, "wCmStatus": 8, "wMsgId": 7, "wMProt": 0},
    "snpReqParams": {
      "wNdpAux": 0,
      "wRBID": 6,
      "wQos": 0,
      "wTof": 3,
      "wDId": 4,
      "wIntfSize": 2,
      "wMpf3": 10,
      "wMpf2": 10,
      "wMpf1": 8,
      "wTM": 1,
      "wRL": 2,
      "wUP": 2,
      "wPR": 1,
      "wNS": 1,
      "wAC": 1,
      "wCA": 1,
      "wVZ": 1,
      "wAddr": 48,
      "wCmStatus": 8,
      "wMProt": 0
    },
    "snpRspParams": {"wIntfSize": 2, "wMpf1": 8, "wCmStatus": 8, "wMsgId": 7, "wMProt": 0},
    "cmpRspParams": {"wCmStatus": 8, "wMsgId": 7, "wMProt": 0},
    "strRspParams": {"wCmStatus": 8, "wMsgId": 7, "wMProt": 0},
    "dtwReqParams": {
      "wNdpAux": 0,
      "wIntfSize": 2,
      "wMpf2": 10,
      "wMpf1": 8,
      "wPrimary": 1,
      "wTM": 1,
      "wRL": 2,
      "wCmStatus": 8,
      "wRBID": 6,
      "wDwId": 12,
      "wDBad": 4,
      "wBE": 32,
      "wData": 256,
      "wDProt": 0,
      "wUser": 0,
      "wMProt": 0
    },
    "ncCmdRspParams": {"wCmStatus": 8, "wMsgId": 7, "wMProt": 0},
    "dtwRspParams": {"wRL": 2, "wCmStatus": 8, "wMsgId": 7, "wMProt": 0},
    "strReqParams": {
      "wIntfSize": 2,
      "wMpf2": 10,
      "wMpf1": 8,
      "wRBID": 6,
      "wCmStatus": 8,
      "wMsgId": 7,
      "wMProt": 0
    },
    "updReqParams": {"wNS": 1, "wAddr": 48, "wCmStatus": 8, "wQos": 0, "wMProt": 0},
    "rbuReqParams": {"wCmStatus": 8, "wRBID": 6, "wRL": 2, "wMProt": 0, "wQos": 0},
    "mrdRspParams": {"wCmStatus": 8, "wMsgId": 7, "wMProt": 0},
    "rbrRspParams": {"wCmStatus": 8, "wMsgId": 7, "wMProt": 0},
    "updRspParams": {"wCmStatus": 8, "wMsgId": 7, "wMProt": 0},
    "rbuRspParams": {"wCmStatus": 8, "wMsgId": 7, "wMProt": 0},
    "rbrReqParams": {
      "wRL": 2,
      "wMW": 1,
      "wPR": 1,
      "wNS": 1,
      "wCA": 1,
      "wAC": 1,
      "wVZ": 1,
      "wIntfSize": 2,
      "wSize": 3,
      "wAddr": 48,
      "wRType": 1,
      "wCmStatus": 8,
      "wRBID": 6,
      "wQos": 0,
      "wMProt": 0,
      "wTof": 3,
      "wMpf1": 8,
      "wNdpAux": 0
    },
    "mrdReqParams": {
      "wNdpAux": 0,
      "wIntfSize": 2,
      "wSize": 3,
      "wMpf2": 10,
      "wMpf1": 8,
      "wTM": 1,
      "wRL": 2,
      "wPR": 1,
      "wNS": 1,
      "wAC": 1,
      "wAddr": 48,
      "wCmStatus": 8,
      "wQos": 0,
      "wMProt": 0
    }
  },
  "concMuxMsgParams": {
    "tx": {
      "ncCmdRsp": {
        "enablePipe": 0,
        "pipeDepth": 2,
        "dpPresent": 0,
        "wNdpBits": 15,
        "wDpBits": 0,
        "protection": "none",
        "dpProtection": "none"
      },
      "dtwRsp": {
        "enablePipe": 0,
        "pipeDepth": 2,
        "dpPresent": 0,
        "wNdpBits": 17,
        "wDpBits": 0,
        "protection": "none",
        "dpProtection": "none"
      },
      "strReq": {
        "enablePipe": 0,
        "pipeDepth": 2,
        "dpPresent": 0,
        "wNdpBits": 41,
        "wDpBits": 0,
        "protection": "none",
        "dpProtection": "none"
      },
      "dtrReq": {
        "enablePipe": 0,
        "pipeDepth": 2,
        "dpPresent": 1,
        "wNdpBits": 26,
        "wDpBits": 256,
        "protection": "none",
        "dpProtection": "none"
      }
    },
    "rx": {
      "cmdReq": {
        "enablePipe": 0,
        "pipeDepth": 2,
        "dpPresent": 0,
        "wNdpBits": 102,
        "wDpBits": 0,
        "protection": "none",
        "dpProtection": "none"
      },
      "strRsp": {
        "enablePipe": 0,
        "pipeDepth": 2,
        "dpPresent": 0,
        "wNdpBits": 15,
        "wDpBits": 0,
        "protection": "none",
        "dpProtection": "none"
      },
      "dtrRsp": {
        "enablePipe": 0,
        "pipeDepth": 2,
        "dpPresent": 0,
        "wNdpBits": 15,
        "wDpBits": 0,
        "protection": "none",
        "dpProtection": "none"
      },
      "dtwReq": {
        "enablePipe": 0,
        "pipeDepth": 2,
        "dpPresent": 1,
        "wNdpBits": 38,
        "wDpBits": 256,
        "protection": "none",
        "dpProtection": "none"
      }
    }
  },
  "cmpInfo": {
    "nRttCtrlEntries": 32,
    "nWttCtrlEntries": 16,
    "nDtrInFlight": 49,
    "nWriteBufferEntries": 4,
    "nWriteRBIDs": 16,
    "nNcCmdInFlightToDii": 20
  },
  "smiPortParams": {
    "tx": [
      {
        "params": {
          "enablePipe": false,
          "pipeDepth": 1,
          "protection": "none",
          "fnMsgClass": ["str_req_"],
          "fPortId": ["2'd0"],
          "fnMsgCmType": ["8'b0111_1010"]
        },
        "name": "smi_tx0_"
      },
      {
        "params": {
          "enablePipe": false,
          "pipeDepth": 1,
          "protection": "none",
          "fnMsgClass": ["nc_cmd_rsp_", "dtw_rsp_"],
          "fPortId": ["2'd1", "2'd1"],
          "fnMsgCmType": ["8'b1111_0001", "8'b1111_0011"]
        },
        "name": "smi_tx1_"
      },
      {
        "params": {
          "enablePipe": false,
          "pipeDepth": 1,
          "protection": "none",
          "fnMsgClass": ["dtr_req_"],
          "fPortId": ["2'd0"],
          "fnMsgCmType": ["8'b1000_????"]
        },
        "name": "smi_tx2_"
      }
    ],
    "rx": [
      {
        "params": {
          "enablePipe": false,
          "pipeDepth": 1,
          "protection": "none",
          "fnMsgClass": ["cmd_req_"],
          "fPortId": ["2'd0"],
          "fnMsgCmType": ["8'b00??_????"]
        },
        "name": "smi_rx0_"
      },
      {
        "params": {
          "enablePipe": false,
          "pipeDepth": 1,
          "protection": "none",
          "fnMsgClass": ["dtr_rsp_", "str_rsp_"],
          "fPortId": ["2'd1", "2'd1"],
          "fnMsgCmType": ["8'b1111_0100", "8'b1111_0111"]
        },
        "name": "smi_rx1_"
      },
      {
        "params": {
          "enablePipe": false,
          "pipeDepth": 1,
          "protection": "none",
          "fnMsgClass": ["dtw_req_"],
          "fPortId": ["2'd0"],
          "fnMsgCmType": ["8'b1001_????"]
        },
        "name": "smi_rx2_"
      }
    ]
  },
  "DataMem": {"Signals": [], "rtlPrefixString": "DII_dataMem", "MemType": "NONE"},
  "interfaces": {
    "axiInt": {
      "params": {
        "wAddr": 48,
        "wArUser": 0,
        "wArId": 10,
        "wAwUser": 0,
        "wAwId": 10,
        "wWUser": 0,
        "wData": 256,
        "wRUser": 0,
        "wBUser": 0,
        "wLen": 8,
        "wSize": 3,
        "wLock": 1,
        "wProt": 3,
        "wQos": 0,
        "wRegion": 0,
        "wResp": 2,
        "wUser": 0
      },
      "name": "axi4_mst_",
      "interface": "InterfaceAXI",
      "direction": "master"
    },
    "clkInt": {
      "params": {"wTestEn": 0, "wClkEn": 0, "wEdgeEn": 0, "wPreEdgeEn": 0, "wRetRst": 0},
      "_SKIP_": false,
      "name": "clk_reg_clk_dom_clk_subdom_",
      "interface": "InterfaceCLK",
      "blkClkGateOn": false,
      "direction": "slave"
    },
    "checkClkInt": {
      "params": {"wTestEn": 0, "wClkEn": 0, "wEdgeEn": 0, "wPreEdgeEn": 0, "wRetRst": 0},
      "_SKIP_": true,
      "name": "",
      "interface": "InterfaceCLK",
      "blkClkGateOn": false,
      "direction": "slave"
    },
    "uIdInt": {
      "params": {"wFUnitId": 4, "wNUnitId": 3, "wRpn": 8, "wNrri": 4},
      "name": "uId_",
      "interface": "InterfaceUnitId",
      "direction": "slave"
    },
    "irqInt": {"name": "irq_", "interface": "InterfaceIRQ", "direction": "master"},
    "apbInt": {
      "params": {"wAddr": 12, "wData": 32, "wPSlverr": 1},
      "_SKIP_": false,
      "name": "apb_",
      "interface": "InterfaceAPB",
      "direction": "slave"
    },
    "qInt": {
      "params": {"channelType": "Q", "wActive": 1},
      "_SKIP_": true,
      "name": "q_",
      "interface": "InterfacePQChannel",
      "direction": "slave"
    },
    "bistInt": {
      "name": "bist_",
      "_SKIP_": true,
      "interface": "InterfaceBIST",
      "direction": "slave"
    },
    "faultInt": {
      "params": {},
      "name": "fault_",
      "_SKIP_": true,
      "interface": "InterfaceFault",
      "direction": "master"
    },
    "smiTxInt": [
      {
        "params": {
          "wSmiVNid": 0,
          "wSmiUser": 0,
          "wSmiTypeAttr": 0,
          "wSmiType": 8,
          "wSmiTxnResp": 0,
          "wSmiTxnHdrRegion": 0,
          "wSmiTxnHdrMemAttr": 0,
          "wSmiTxnHdrMaxBsize": 0,
          "wSmiTxnHdrBtype": 0,
          "wSmiTxnHdrBsize": 0,
          "wSmiTxnHdrAtomic": 0,
          "wSmiTier": 0,
          "wSmiTid": 6,
          "wSmiSteer": 0,
          "wSmiSid": 6,
          "wSmiSeqnum": 0,
          "wSmiSec": 0,
          "wSmiRoute": 0,
          "wSmiQos": 0,
          "wSmiProtFail": 0,
          "wSmiPri": 0,
          "wSmiPoison": 0,
          "wSmiPktType": 0,
          "wSmiPktId": 0,
          "wSmiOrderingModel": 0,
          "wSmiOrderingId": 0,
          "wSmiNDPLen": 8,
          "wSmiNDP": 109,
          "wSmiMultiMask": 0,
          "wSmiMultiLabel": 0,
          "wSmiMsgSec": 0,
          "wSmiMsgQos": 0,
          "wSmiLen": 0,
          "wSmiId": 7,
          "wSmiErr": 0,
          "wSmiDPuser": 0,
          "wSmiDPresp": 0,
          "wSmiDPlast": 0,
          "wSmiDPid": 0,
          "wSmiDPdummy": 0,
          "wSmiDPdata": 0,
          "wSmiDPbe": 0,
          "wSmiDPErr": 0,
          "wSmiChlId": 0,
          "wSmiAddr": 0,
          "nSmiVC": 1,
          "nSmiDPvc": 0
        },
        "name": "smi_tx0_",
        "interface": "InterfaceSMI",
        "direction": "master"
      },
      {
        "params": {
          "wSmiVNid": 0,
          "wSmiUser": 0,
          "wSmiTypeAttr": 0,
          "wSmiType": 8,
          "wSmiTxnResp": 0,
          "wSmiTxnHdrRegion": 0,
          "wSmiTxnHdrMemAttr": 0,
          "wSmiTxnHdrMaxBsize": 0,
          "wSmiTxnHdrBtype": 0,
          "wSmiTxnHdrBsize": 0,
          "wSmiTxnHdrAtomic": 0,
          "wSmiTier": 0,
          "wSmiTid": 6,
          "wSmiSteer": 0,
          "wSmiSid": 6,
          "wSmiSeqnum": 0,
          "wSmiSec": 0,
          "wSmiRoute": 0,
          "wSmiQos": 0,
          "wSmiProtFail": 0,
          "wSmiPri": 0,
          "wSmiPoison": 0,
          "wSmiPktType": 0,
          "wSmiPktId": 0,
          "wSmiOrderingModel": 0,
          "wSmiOrderingId": 0,
          "wSmiNDPLen": 8,
          "wSmiNDP": 109,
          "wSmiMultiMask": 0,
          "wSmiMultiLabel": 0,
          "wSmiMsgSec": 0,
          "wSmiMsgQos": 0,
          "wSmiLen": 0,
          "wSmiId": 7,
          "wSmiErr": 0,
          "wSmiDPuser": 0,
          "wSmiDPresp": 0,
          "wSmiDPlast": 0,
          "wSmiDPid": 0,
          "wSmiDPdummy": 0,
          "wSmiDPdata": 0,
          "wSmiDPbe": 0,
          "wSmiDPErr": 0,
          "wSmiChlId": 0,
          "wSmiAddr": 0,
          "nSmiVC": 1,
          "nSmiDPvc": 0
        },
        "name": "smi_tx1_",
        "interface": "InterfaceSMI",
        "direction": "master"
      },
      {
        "params": {
          "wSmiVNid": 0,
          "wSmiUser": 0,
          "wSmiTypeAttr": 0,
          "wSmiType": 8,
          "wSmiTxnResp": 0,
          "wSmiTxnHdrRegion": 0,
          "wSmiTxnHdrMemAttr": 0,
          "wSmiTxnHdrMaxBsize": 0,
          "wSmiTxnHdrBtype": 0,
          "wSmiTxnHdrBsize": 0,
          "wSmiTxnHdrAtomic": 0,
          "wSmiTier": 0,
          "wSmiTid": 6,
          "wSmiSteer": 0,
          "wSmiSid": 6,
          "wSmiSeqnum": 0,
          "wSmiSec": 0,
          "wSmiRoute": 0,
          "wSmiQos": 0,
          "wSmiProtFail": 0,
          "wSmiPri": 0,
          "wSmiPoison": 0,
          "wSmiPktType": 0,
          "wSmiPktId": 0,
          "wSmiOrderingModel": 0,
          "wSmiOrderingId": 0,
          "wSmiNDPLen": 8,
          "wSmiNDP": 38,
          "wSmiMultiMask": 0,
          "wSmiMultiLabel": 0,
          "wSmiMsgSec": 0,
          "wSmiMsgQos": 0,
          "wSmiLen": 0,
          "wSmiId": 7,
          "wSmiErr": 0,
          "wSmiDPuser": 48,
          "wSmiDPresp": 0,
          "wSmiDPlast": 1,
          "wSmiDPid": 0,
          "wSmiDPdummy": 0,
          "wSmiDPdata": 256,
          "wSmiDPbe": 0,
          "wSmiDPErr": 0,
          "wSmiChlId": 0,
          "wSmiAddr": 0,
          "nSmiVC": 1,
          "nSmiDPvc": 1
        },
        "name": "smi_tx2_",
        "interface": "InterfaceSMI",
        "direction": "master"
      }
    ],
    "smiRxInt": [
      {
        "params": {
          "wSmiVNid": 0,
          "wSmiUser": 0,
          "wSmiTypeAttr": 0,
          "wSmiType": 8,
          "wSmiTxnResp": 0,
          "wSmiTxnHdrRegion": 0,
          "wSmiTxnHdrMemAttr": 0,
          "wSmiTxnHdrMaxBsize": 0,
          "wSmiTxnHdrBtype": 0,
          "wSmiTxnHdrBsize": 0,
          "wSmiTxnHdrAtomic": 0,
          "wSmiTier": 0,
          "wSmiTid": 6,
          "wSmiSteer": 0,
          "wSmiSid": 6,
          "wSmiSeqnum": 0,
          "wSmiSec": 0,
          "wSmiRoute": 0,
          "wSmiQos": 0,
          "wSmiProtFail": 0,
          "wSmiPri": 0,
          "wSmiPoison": 0,
          "wSmiPktType": 0,
          "wSmiPktId": 0,
          "wSmiOrderingModel": 0,
          "wSmiOrderingId": 0,
          "wSmiNDPLen": 8,
          "wSmiNDP": 109,
          "wSmiMultiMask": 0,
          "wSmiMultiLabel": 0,
          "wSmiMsgSec": 0,
          "wSmiMsgQos": 0,
          "wSmiLen": 0,
          "wSmiId": 7,
          "wSmiErr": 1,
          "wSmiDPuser": 0,
          "wSmiDPresp": 0,
          "wSmiDPlast": 0,
          "wSmiDPid": 0,
          "wSmiDPdummy": 0,
          "wSmiDPdata": 0,
          "wSmiDPbe": 0,
          "wSmiDPErr": 0,
          "wSmiChlId": 0,
          "wSmiAddr": 0,
          "nSmiVC": 1,
          "nSmiDPvc": 0
        },
        "name": "smi_rx0_",
        "interface": "InterfaceSMI",
        "direction": "slave"
      },
      {
        "params": {
          "wSmiVNid": 0,
          "wSmiUser": 0,
          "wSmiTypeAttr": 0,
          "wSmiType": 8,
          "wSmiTxnResp": 0,
          "wSmiTxnHdrRegion": 0,
          "wSmiTxnHdrMemAttr": 0,
          "wSmiTxnHdrMaxBsize": 0,
          "wSmiTxnHdrBtype": 0,
          "wSmiTxnHdrBsize": 0,
          "wSmiTxnHdrAtomic": 0,
          "wSmiTier": 0,
          "wSmiTid": 6,
          "wSmiSteer": 0,
          "wSmiSid": 6,
          "wSmiSeqnum": 0,
          "wSmiSec": 0,
          "wSmiRoute": 0,
          "wSmiQos": 0,
          "wSmiProtFail": 0,
          "wSmiPri": 0,
          "wSmiPoison": 0,
          "wSmiPktType": 0,
          "wSmiPktId": 0,
          "wSmiOrderingModel": 0,
          "wSmiOrderingId": 0,
          "wSmiNDPLen": 8,
          "wSmiNDP": 109,
          "wSmiMultiMask": 0,
          "wSmiMultiLabel": 0,
          "wSmiMsgSec": 0,
          "wSmiMsgQos": 0,
          "wSmiLen": 0,
          "wSmiId": 7,
          "wSmiErr": 1,
          "wSmiDPuser": 0,
          "wSmiDPresp": 0,
          "wSmiDPlast": 0,
          "wSmiDPid": 0,
          "wSmiDPdummy": 0,
          "wSmiDPdata": 0,
          "wSmiDPbe": 0,
          "wSmiDPErr": 0,
          "wSmiChlId": 0,
          "wSmiAddr": 0,
          "nSmiVC": 1,
          "nSmiDPvc": 0
        },
        "name": "smi_rx1_",
        "interface": "InterfaceSMI",
        "direction": "slave"
      },
      {
        "params": {
          "wSmiVNid": 0,
          "wSmiUser": 0,
          "wSmiTypeAttr": 0,
          "wSmiType": 8,
          "wSmiTxnResp": 0,
          "wSmiTxnHdrRegion": 0,
          "wSmiTxnHdrMemAttr": 0,
          "wSmiTxnHdrMaxBsize": 0,
          "wSmiTxnHdrBtype": 0,
          "wSmiTxnHdrBsize": 0,
          "wSmiTxnHdrAtomic": 0,
          "wSmiTier": 0,
          "wSmiTid": 6,
          "wSmiSteer": 0,
          "wSmiSid": 6,
          "wSmiSeqnum": 0,
          "wSmiSec": 0,
          "wSmiRoute": 0,
          "wSmiQos": 0,
          "wSmiProtFail": 0,
          "wSmiPri": 0,
          "wSmiPoison": 0,
          "wSmiPktType": 0,
          "wSmiPktId": 0,
          "wSmiOrderingModel": 0,
          "wSmiOrderingId": 0,
          "wSmiNDPLen": 8,
          "wSmiNDP": 38,
          "wSmiMultiMask": 0,
          "wSmiMultiLabel": 0,
          "wSmiMsgSec": 0,
          "wSmiMsgQos": 0,
          "wSmiLen": 0,
          "wSmiId": 7,
          "wSmiErr": 1,
          "wSmiDPuser": 48,
          "wSmiDPresp": 0,
          "wSmiDPlast": 1,
          "wSmiDPid": 0,
          "wSmiDPdummy": 0,
          "wSmiDPdata": 256,
          "wSmiDPbe": 0,
          "wSmiDPErr": 0,
          "wSmiChlId": 0,
          "wSmiAddr": 0,
          "nSmiVC": 1,
          "nSmiDPvc": 1
        },
        "name": "smi_rx2_",
        "interface": "InterfaceSMI",
        "direction": "slave"
      }
    ]
  },
  "csr": {
    "addressWidth": 12,
    "width": 32,
    "spaceBlock": [
      {
        "baseAddress": 0,
        "registers": [
          {
            "name": "DIIUIDR",
            "description": "DIIU Identification Register",
            "csrDescription": "DIIU Identification Register",
            "addressOffset": 0,
            "fields": [
              {
                "name": "RPN",
                "bitOffset": 0,
                "bitWidth": 8,
                "access": "RO",
                "hardware": "RO",
                "linkOp": "NULL",
                "opOrder": "NULL",
                "description": "DIIU Register Page Number (within its NRR)",
                "resetOverloadFn": "return primary.rpn;",
                "reset": 0
              },
              {
                "name": "NRRI",
                "bitOffset": 8,
                "bitWidth": 4,
                "access": "RO",
                "hardware": "RO",
                "linkOp": "NULL",
                "opOrder": "NULL",
                "description": "Identifier of the Ncore 3 Register Region\nin which this DIIU resides",
                "resetOverloadFn": "return primary.nrri;",
                "reset": 0
              },
              {
                "name": "NUnitId",
                "bitOffset": 12,
                "bitWidth": 12,
                "access": "RO",
                "hardware": "RO",
                "linkOp": "NULL",
                "opOrder": "NULL",
                "description": "Ncore 3 Unit identifier. ",
                "reset": 0,
                "resetOverloadFn": "return primary.nUnitId;"
              },
              {
                "name": "Rsvd1",
                "bitOffset": 24,
                "bitWidth": 7,
                "access": "RO",
                "hardware": "RO",
                "reset": 0,
                "linkOp": "NULL",
                "opOrder": "NULL",
                "scope": "",
                "description": "Reserved"
              },
              {
                "name": "Valid",
                "bitOffset": 31,
                "bitWidth": 1,
                "access": "RO",
                "hardware": "RO",
                "linkOp": "NULL",
                "opOrder": "NULL",
                "description": "Value of 1 validates this register. This bit\nis set to 1 if the DIIU is implemented.",
                "reset": 1
              }
            ],
            "specialImplementation": false
          },
          {
            "name": "DIIUFUIDR",
            "description": "DIIU Fabric Unit Identification Register",
            "csrDescription": "DIIU Fabric Unit Identification Register",
            "addressOffset": 4,
            "fields": [
              {
                "name": "FUnitId",
                "bitOffset": 0,
                "bitWidth": 16,
                "access": "RO",
                "hardware": "RO",
                "reset": 0,
                "resetOverloadFn": "return primary.fUnitId;",
                "linkOp": "NULL",
                "opOrder": "NULL",
                "description": "Fabric Unit Identifier of the unit"
              },
              {
                "name": "Rsvd1",
                "bitOffset": 16,
                "bitWidth": 16,
                "access": "RO",
                "hardware": "RO",
                "reset": 0,
                "linkOp": "NULL",
                "opOrder": "NULL",
                "scope": "",
                "description": "Reserved"
              }
            ],
            "specialImplementation": false
          },
          {
            "name": "DIIUTAR",
            "description": "DIIU Transaction Activity Register",
            "csrDescription": "DIIU Transaction Activity Register",
            "addressOffset": 64,
            "fields": [
              {
                "name": "TransActv",
                "bitOffset": 0,
                "bitWidth": 1,
                "access": "RO",
                "hardware": "RW",
                "reset": 0,
                "linkOp": "NULL",
                "opOrder": "NULL",
                "scope": "All",
                "description": "This bit is set when there is one or more active transactions inside the DIIU."
              },
              {
                "name": "Rsvd1",
                "bitOffset": 1,
                "bitWidth": 31,
                "access": "RO",
                "hardware": "RO",
                "reset": 0,
                "linkOp": "NULL",
                "opOrder": "NULL",
                "scope": "",
                "description": "Reserved"
              }
            ],
            "specialImplementation": false
          },
          {
            "name": "DIIUUEDR",
            "description": "DIIU Uncorrectable Error Detect Register",
            "csrDescription": "DIIU Uncorrectable Error Detect Register",
            "addressOffset": 280,
            "fields": [
              {
                "name": "ProtErrDetEn",
                "bitOffset": 0,
                "bitWidth": 1,
                "access": "RW",
                "hardware": "RO",
                "reset": 0,
                "linkOp": "NULL",
                "opOrder": "NULL",
                "description": "AXI downstream protocol error detect enable: When set, errors will be detected from the downstream AXI interface."
              },
              {
                "name": "TransErrDetEn",
                "bitOffset": 1,
                "bitWidth": 1,
                "access": "RW",
                "hardware": "RO",
                "reset": 0,
                "linkOp": "NULL",
                "opOrder": "NULL",
                "description": "Concerto Transport error detect enable: When set, errors will be detected from the Concerto Transport."
              },
              {
                "name": "Rsvd1",
                "bitOffset": 2,
                "bitWidth": 30,
                "access": "RO",
                "hardware": "RO",
                "reset": 0,
                "linkOp": "NULL",
                "opOrder": "NULL",
                "scope": "",
                "description": "Reserved"
              }
            ],
            "specialImplementation": false
          },
          {
            "name": "DIIUUEIR",
            "description": "DIIU Uncorrectable Error Interrupt Register",
            "csrDescription": "DIIU Uncorrectable Error Interrupt Register",
            "addressOffset": 284,
            "fields": [
              {
                "name": "ProtErrIntEn",
                "bitOffset": 0,
                "bitWidth": 1,
                "access": "RW",
                "hardware": "RO",
                "reset": 0,
                "linkOp": "NULL",
                "opOrder": "NULL",
                "description": "Downstream AXI uncorrectable error interrupt enable."
              },
              {
                "name": "TransErrIntEn",
                "bitOffset": 1,
                "bitWidth": 1,
                "access": "RW",
                "hardware": "RO",
                "reset": 0,
                "linkOp": "NULL",
                "opOrder": "NULL",
                "description": "Concerto Transport uncorrectable error interrupt enable."
              },
              {
                "name": "Rsvd1",
                "bitOffset": 2,
                "bitWidth": 30,
                "access": "RO",
                "hardware": "RO",
                "reset": 0,
                "linkOp": "NULL",
                "opOrder": "NULL",
                "scope": "",
                "description": "Reserved"
              }
            ],
            "specialImplementation": false
          },
          {
            "name": "DIIUUESR",
            "description": "DIIU Uncorrectable Error Status Register",
            "csrDescription": "DIIU Uncorrectable Error Status Register",
            "addressOffset": 288,
            "fields": [
              {
                "name": "ErrVld",
                "bitOffset": 0,
                "bitWidth": 1,
                "access": "W1C",
                "hardware": "RW",
                "reset": 0,
                "linkOp": "NULL",
                "opOrder": "NULL",
                "scope": "All",
                "description": "If this bit is set, Error information is logged in status and location registers. Writing a one to the Correctable Error Valid bit clears the Correctable Error Valid bit."
              },
              {
                "name": "Rsvd1",
                "bitOffset": 1,
                "bitWidth": 3,
                "access": "RO",
                "hardware": "RO",
                "reset": 0,
                "linkOp": "NULL",
                "opOrder": "NULL",
                "scope": "",
                "description": "Reserved"
              },
              {
                "name": "ErrType",
                "bitOffset": 4,
                "bitWidth": 5,
                "access": "RO",
                "hardware": "RW",
                "reset": 0,
                "linkOp": "NULL",
                "opOrder": "NULL",
                "scope": "All",
                "description": "This field indicates the logged error type"
              },
              {
                "name": "Rsvd2",
                "bitOffset": 9,
                "bitWidth": 7,
                "access": "RO",
                "hardware": "RO",
                "reset": 0,
                "linkOp": "NULL",
                "opOrder": "NULL",
                "scope": "",
                "description": "Reserved"
              },
              {
                "name": "ErrInfo",
                "bitOffset": 16,
                "bitWidth": 16,
                "access": "RO",
                "hardware": "RW",
                "reset": 0,
                "linkOp": "NULL",
                "opOrder": "NULL",
                "scope": "All",
                "description": "This field indicates additional information about logged error"
              }
            ],
            "specialImplementation": false
          },
          {
            "name": "DIIUUELR0",
            "description": "DIIU Uncorrectable Error Location Registers 0",
            "csrDescription": "DIIU Uncorrectable Error Location Registers 0",
            "addressOffset": 292,
            "fields": [
              {
                "name": "ErrEntry",
                "bitOffset": 0,
                "bitWidth": 20,
                "access": "RW",
                "hardware": "WO",
                "reset": 0,
                "linkOp": "NULL",
                "opOrder": "NULL",
                "description": "This field indicates the entry or the set in which the logged error was detected",
                "scope": "All"
              },
              {
                "name": "ErrWay",
                "bitOffset": 20,
                "bitWidth": 6,
                "access": "RW",
                "hardware": "WO",
                "reset": 0,
                "linkOp": "NULL",
                "opOrder": "NULL",
                "description": "This field indicates the way in which the logged error was detected",
                "scope": "All"
              },
              {
                "name": "ErrWord",
                "bitOffset": 26,
                "bitWidth": 6,
                "access": "RW",
                "hardware": "WO",
                "reset": 0,
                "linkOp": "NULL",
                "opOrder": "NULL",
                "description": "This field indicates the data word in which the logged error was detected",
                "scope": "All"
              }
            ],
            "specialImplementation": false
          },
          {
            "name": "DIIUUELR1",
            "description": "DIIU Uncorrectable Error Location Registers 1",
            "csrDescription": "DIIU Uncorrectable Error Location Registers 1",
            "addressOffset": 296,
            "fields": [
              {
                "name": "ErrAddr",
                "bitOffset": 0,
                "bitWidth": 20,
                "access": "RW",
                "hardware": "WO",
                "reset": 0,
                "linkOp": "NULL",
                "opOrder": "NULL",
                "description": "This field contains the high-order address bits of the transaction that encountered the error",
                "scope": "All"
              },
              {
                "name": "Rsvd1",
                "bitOffset": 20,
                "bitWidth": 12,
                "access": "RO",
                "hardware": "RO",
                "reset": 0,
                "linkOp": "NULL",
                "opOrder": "NULL",
                "scope": "",
                "description": "Reserved"
              }
            ],
            "specialImplementation": false
          },
          {
            "name": "DIIUUESAR",
            "description": "DIIU Uncorrectable Error Status Alias Register",
            "csrDescription": "DIIU Uncorrectable Error Status Alias Register",
            "addressOffset": 300,
            "fields": [
              {
                "name": "ErrVld",
                "bitOffset": 0,
                "access": "RW",
                "hardware": "RO",
                "reset": 0,
                "link": "xESR.ErrVld",
                "linkOp": "SOW",
                "opOrder": "HW",
                "scope": "All",
                "description": "Alias bit for setting error valid filed of xUESR",
                "bitWidth": 1
              },
              {
                "name": "Rsvd1",
                "bitOffset": 1,
                "bitWidth": 3,
                "access": "RO",
                "hardware": "RO",
                "reset": 0,
                "linkOp": "NULL",
                "opOrder": "NULL",
                "scope": "",
                "description": "Reserved"
              },
              {
                "name": "ErrType",
                "bitOffset": 4,
                "access": "RW",
                "hardware": "RO",
                "reset": 0,
                "link": "xESR.ErrType",
                "linkOp": "SOW",
                "opOrder": "HW",
                "scope": "All",
                "description": "Alias bit for setting error type field of xUESR ",
                "bitWidth": 5
              },
              {
                "name": "Rsvd2",
                "bitOffset": 9,
                "bitWidth": 7,
                "access": "RO",
                "hardware": "RO",
                "reset": 0,
                "linkOp": "NULL",
                "opOrder": "NULL",
                "scope": "",
                "description": "Reserved"
              },
              {
                "name": "ErrInfo",
                "bitOffset": 16,
                "access": "RW",
                "hardware": "RO",
                "reset": 0,
                "link": "xESR.ErrInfo",
                "linkOp": "SOW",
                "opOrder": "HW",
                "scope": "All",
                "description": "Alias bit for setting errro info field of xUESR",
                "bitWidth": 16
              }
            ],
            "specialImplementation": false
          },
          {
            "name": "DIIUUEVIR",
            "description": "DIIU Unit Engineering Version Id Register",
            "csrDescription": "DIIU Unit Engineering Version Id Register",
            "addressOffset": 4032,
            "fields": [
              {
                "name": "EngVerId",
                "bitOffset": 0,
                "bitWidth": 32,
                "access": "RO",
                "hardware": "RO",
                "linkOp": "NULL",
                "opOrder": "NULL",
                "description": "Engineering Version Identifier",
                "scope": "Engg",
                "reset": 0
              }
            ],
            "specialImplementation": false
          },
          {
            "name": "DIIUINFOR",
            "description": "DIIU Information Register ",
            "csrDescription": "DIIU Information Register ",
            "addressOffset": 4036,
            "fields": [
              {
                "name": "ImplVer",
                "bitOffset": 0,
                "bitWidth": 8,
                "access": "RO",
                "hardware": "RO",
                "linkOp": "NULL",
                "opOrder": "NULL",
                "description": "Implementation Version",
                "scope": "All",
                "reset": 0
              },
              {
                "name": "UT",
                "bitOffset": 8,
                "bitWidth": 4,
                "access": "RO",
                "hardware": "RO",
                "linkOp": "NULL",
                "opOrder": "NULL",
                "description": "Unit Type",
                "scope": "All",
                "reset": 10
              },
              {
                "name": "Rsvd1",
                "bitOffset": 12,
                "bitWidth": 19,
                "access": "RO",
                "hardware": "RO",
                "reset": 0,
                "linkOp": "NULL",
                "opOrder": "NULL",
                "scope": "",
                "description": "Reserved"
              },
              {
                "name": "Valid",
                "bitOffset": 31,
                "bitWidth": 1,
                "access": "RO",
                "hardware": "RO",
                "linkOp": "NULL",
                "opOrder": "NULL",
                "description": "Implemented",
                "scope": "All",
                "reset": 1
              }
            ],
            "specialImplementation": false
          }
        ]
      }
    ]
  }
}